Workbook

Sheet SCB
A1: CODIGO | B1: CEDULA | C1: NOMBRE | D1: FECHA | E1: TIPO | F1: BASE IVA | G1: BASE 0 | H1: IMPUESTOS | I1: RETENCION | J1: SALDO | K1: DOCUMENTO | L1: MONTO
A2: 432 | B2: 190123626001 | C2: ASEGURADORA DEL SUR C.A. | D2: 46042 | E2: FE | F2: 50638 | G2: 6100.38 | H2: 5304.68 | I2: 0 | J2: 795.7 | K2: 0 | L2: 6100.38
A3: 1416 | B3: 201879962001 | C3: MONTALVO POVEDA IVETTE ANDREA | D3: 46044 | E3: FE | F3: 238 | G3: 98.25 | H3: 0 | I3: 100 | J3: 0 | K3: 1.75 | L3: 98.25
A4: 1416 | B4: 201879962001 | C4: MONTALVO POVEDA IVETTE ANDREA | D4: 46044 | E4: FE | F4: 240 | G4: 98.25 | H4: 0 | I4: 100 | J4: 0 | K4: 1.75 | L4: 98.25
A5: 1310 | B5: 501639371001 | C5: VIZUETE MATA ZOILA TERESA | D5: 46030 | E5: FE | F5: 2 | G5: 180 | H5: 200 | I5: 0 | J5: 30 | K5: 50 | L5: 0
A6: 1794 | B6: 602001810001 | C6: CHAVEZ ZULA ZOILA | D6: 46028 | E6: BV | F6: 612 | G6: 10 | H6: 0 | I6: 10 | J6: 0 | K6: 0 | L6: 10
A7: 1794 | B7: 602001810001 | C7: CHAVEZ ZULA ZOILA | D7: 46029 | E7: BV | F7: 613 | G7: 10 | H7: 0 | I7: 10 | J7: 0 | K7: 0 | L7: 10
A8: 1794 | B8: 602001810001 | C8: CHAVEZ ZULA ZOILA | D8: 46030 | E8: BV | F8: 614 | G8: 10 | H8: 0 | I8: 10 | J8: 0 | K8: 0 | L8: 10
A9: 1794 | B9: 602001810001 | C9: CHAVEZ ZULA ZOILA | D9: 46030 | E9: BV | F9: 615 | G9: 10 | H9: 0 | I9: 10 | J9: 0 | K9: 0 | L9: 10
A10: 1794 | B10: 602001810001 | C10: CHAVEZ ZULA ZOILA | D10: 46032 | E10: BV | F10: 617 | G10: 10 | H10: 0 | I10: 10 | J10: 0 | K10: 0 | L10: 10
A11: 1794 | B11: 602001810001 | C11: CHAVEZ ZULA ZOILA | D11: 46032 | E11: BV | F11: 618 | G11: 10 | H11: 0 | I11: 10 | J11: 0 | K11: 0 | L11: 10
A12: 1794 | B12: 602001810001 | C12: CHAVEZ ZULA ZOILA | D12: 46037 | E12: BV | F12: 620 | G12: 10 | H12: 0 | I12: 10 | J12: 0 | K12: 0 | L12: 10
A13: 1794 | B13: 602001810001 | C13: CHAVEZ ZULA ZOILA | D13: 46038 | E13: BV | F13: 621 | G13: 10 | H13: 0 | I13: 10 | J13: 0 | K13: 0 | L13: 10
... A137: 1579 | B137: 1792848776001 | C137: FILTROFAST CIA.LTDA. | D137: 46046 | E137: FE | F137: 33279 | G137: 255.91 | H137: 235.32 | I137: 0 | J137: 35.3 | K137: 14.71 | L137: 255.91
A138: 1522 | B138: 1792967724001 | C138: MEGAWATT-ECUADOR S.A. | D138: 46052 | E138: FE | F138: A000001751 | G138: 21.75 | H138: 20 | I138: 0 | J138: 3 | K138: 1.25 | L138: 0
A139: 1522 | B139: 1792967724001 | C139: MEGAWATT-ECUADOR S.A. | D139: 46053 | E139: ND | F139: 1751 | G139: 21.75 | H139: 21.75 | I139: 0 | J139: 0 | K139: 0 | L139: 0
A140: 1840 | B140: 1793025692001 | C140: PROBEMOTOR CIA.LTDA. | D140: 46052 | E140: FE | F140: 19434 | G140: 245.34 | H140: 225.6 | I140: 0 | J140: 33.84 | K140: 14.1 | L140: 245.34
A141: 1410 | B141: 1793107958001 | C141: SZK DEL ECUADOR S.A. | D141: 46027 | E141: FE | F141: 4023 | G141: 203.56 | H141: 177.01 | I141: 0 | J141: 26.55 | K141: 0 | L141: 203.56
A142: 1410 | B142: 1793107958001 | C142: SZK DEL ECUADOR S.A. | D142: 46027 | E142: FE | F142: 4022 | G142: 135.54 | H142: 117.86 | I142: 0 | J142: 17.68 | K142: 0 | L142: 135.54
A143: 1410 | B143: 1793107958001 | C143: SZK DEL ECUADOR S.A. | D143: 46028 | E143: FE | F143: 5329 | G143: 946.58 | H143: 823.11 | I143: 0 | J143: 123.47 | K143: 0 | L143: 946.58
A144: 1410 | B144: 1793107958001 | C144: SZK DEL ECUADOR S.A. | D144: 46028 | E144: FE | F144: 5333 | G144: 128.03 | H144: 111.33 | I144: 0 | J144: 16.7 | K144: 0 | L144: 128.03
A145: 1410 | B145: 1793107958001 | C145: SZK DEL ECUADOR S.A. | D145: 46028 | E145: FE | F145: 7686 | G145: 530.75 | H145: 461.52 | I145: 0 | J145: 69.23 | K145: 0 | L145: 530.75
A146: 1410 | B146: 1793107958001 | C146: SZK DEL ECUADOR S.A. | D146: 46028 | E146: FE | F146: 5321 | G146: 297 | H146: 258.26 | I146: 0 | J146: 38.74 | K146: 0 | L146: 297
A147: 1410 | B147: 1793107958001 | C147: SZK DEL ECUADOR S.A. | D147: 46028 | E147: FE | F147: 7691 | G147: 1046.3 | H147: 909.83 | I147: 0 | J147: 136.47 | K147: 0 | L147: 1046.3
A148: 1410 | B148: 1793107958001 | C148: SZK DEL ECUADOR S.A. | D148: 46029 | E148: FE | F148: 7701 | G148: 41.61 | H148: 36.18 | I148: 0 | J148: 5.43 | K148: 0 | L148: 41.61
A149: 1410 | B149: 1793107958001 | C149: SZK DEL ECUADOR S.A. | D149: 46029 | E149: FE | F149: 5338 | G149: 299.23 | H149: 260.2 | I149: 0 | J149: 39.03 | K149: 0 | L149: 299.23
A150: 1410 | B150: 1793107958001 | C150: SZK DEL ECUADOR S.A. | D150: 46029 | E150: FE | F150: 5336 | G150: 340 | H150: 295.65 | I150: 0 | J150: 44.35 | K150: 0 | L150: 340
... A168: 1410 | B168: 1793107958001 | C168: SZK DEL ECUADOR S.A. | D168: 46032 | E168: FE | F168: 7730 | G168: 284.28 | H168: 247.2 | I168: 0 | J168: 37.08 | K168: 0 | L168: 284.28
A169: 1410 | B169: 1793107958001 | C169: SZK DEL ECUADOR S.A. | D169: 46032 | E169: FE | F169: A00007724 | G169: 48.3 | H169: 42 | I169: 0 | J169: 6.3 | K169: 0 | L169: 0
A170: 1410 | B170: 1793107958001 | C170: SZK DEL ECUADOR S.A. | D170: 46032 | E170: FE | F170: 7727 | G170: 102.2 | H170: 88.87 | I170: 0 | J170: 13.33 | K170: 0 | L170: 102.2
A171: 1410 | B171: 1793107958001 | C171: SZK DEL ECUADOR S.A. | D171: 46034 | E171: FE | F171: 7724 | G171: 43.47 | H171: 37.8 | I171: 0 | J171: 5.67 | K171: 0 | L171: 43.47
A172: 1410 | B172: 1793107958001 | C172: SZK DEL ECUADOR S.A. | D172: 46034 | E172: ND | F172: 900007724 | G172: 48.3 | H172: 48.3 | I172: 0 | J172: 0 | K172: 0 | L172: 0
A173: 1410 | B173: 1793107958001 | C173: SZK DEL ECUADOR S.A. | D173: 46035 | E173: FE | F173: 7741 | G173: 684.97 | H173: 595.63 | I173: 0 | J173: 89.34 | K173: 0 | L173: 684.97
A174: 1410 | B174: 1793107958001 | C174: SZK DEL ECUADOR S.A. | D174: 46035 | E174: FE | F174: 5381 | G174: 1105.1 | H174: 960.96 | I174: 0 | J174: 144.14 | K174: 0 | L174: 1105.1
A175: 1410 | B175: 1793107958001 | C175: SZK DEL ECUADOR S.A. | D175: 46035 | E175: FE | F175: 7737 | G175: 78.18 | H175: 67.98 | I175: 0 | J175: 10.2 | K175: 0 | L175: 78.18
A176: 1410 | B176: 1793107958001 | C176: SZK DEL ECUADOR S.A. | D176: 46035 | E176: FE | F176: 7740 | G176: 466.64 | H176: 405.77 | I176: 0 | J176: 60.87 | K176: 0 | L176: 466.64
A177: 1410 | B177: 1793107958001 | C177: SZK DEL ECUADOR S.A. | D177: 46035 | E177: FE | F177: 7746 | G177: 26.73 | H177: 23.24 | I177: 0 | J177: 3.49 | K177: 0 | L177: 26.73
A178: 1410 | B178: 1793107958001 | C178: SZK DEL ECUADOR S.A. | D178: 46036 | E178: FE | F178: 5391 | G178: 239.2 | H178: 208 | I178: 0 | J178: 31.2 | K178: 0 | L178: 239.2
A179: 1410 | B179: 1793107958001 | C179: SZK DEL ECUADOR S.A. | D179: 46036 | E179: FE | F179: 7756 | G179: 675.36 | H179: 587.27 | I179: 0 | J179: 88.09 | K179: 0 | L179: 675.36
A180: 1410 | B180: 1793107958001 | C180: SZK DEL ECUADOR S.A. | D180: 46036 | E180: FE | F180: 5386 | G180: 193.69 | H180: 168.43 | I180: 0 | J180: 25.26 | K180: 0 | L180: 193.69
A181: 1410 | B181: 1793107958001 | C181: SZK DEL ECUADOR S.A. | D181: 46037 | E181: FE | F181: 5396 | G181: 24.1 | H181: 20.96 | I181: 0 | J181: 3.14 | K181: 0 | L181: 24.1
... A648: 1836 | B648: 1804848115001 | C648: REINOSO SALAS YAJAIRA CAROLINA | D648: 46051 | E648: FE | F648: 114 | G648: 43.5 | H648: 40 | I648: 0 | J648: 6 | K648: 2.5 | L648: 43.5
A649: 1809 | B649: 1805135306001 | C649: MANTILLA MARIÑO ISAAC GIOVANNI | D649: 46029 | E649: FE | F649: A000000029 | G649: 180 | H649: 0 | I649: 180 | J649: 0 | K649: 0 | L649: 0
A650: 1809 | B650: 1805135306001 | C650: MANTILLA MARIÑO ISAAC GIOVANNI | D650: 46042 | E650: ND | F650: 900000029 | G650: 180 | H650: 0 | I650: 180 | J650: 0 | K650: 0 | L650: 0
A651: 1809 | B651: 1805135306001 | C651: MANTILLA MARIÑO ISAAC GIOVANNI | D651: 46042 | E651: FE | F651: 29 | G651: 180 | H651: 0 | I651: 180 | J651: 0 | K651: 0 | L651: 180
A652: 1816 | B652: 1805237821001 | C652: NARANJO ROMERO PRISCILA GRACE | D652: 46050 | E652: FE | F652: 82 | G652: 25.62 | H652: 25 | I652: 0 | J652: 3.75 | K652: 3.13 | L652: 25.62
A653: 1549 | B653: 1805448196 | C653: SILVA MESIAS GRACIELA ELIZABETH | D653: 46051 | E653: LC | F653: 233 | G653: 39.14 | H653: 23.6 | I653: 12 | J653: 3.54 | K653: 0 | L653: 39.14
A654: 518 | B654: 1860000210001 | C654: G.A.D. MUNICIPALIDAD DE AMBATO | D654: 46036 | E654: OT | F654: 9135700 | G654: 118.68 | H654: 0 | I654: 118.68 | J654: 0 | K654: 0 | L654: 0
A655: 518 | B655: 1860000210001 | C655: G.A.D. MUNICIPALIDAD DE AMBATO | D655: 46036 | E655: OT | F655: 9135701 | G655: 136.03 | H655: 0 | I655: 136.03 | J655: 0 | K655: 0 | L655: 0
A656: 518 | B656: 1860000210001 | C656: G.A.D. MUNICIPALIDAD DE AMBATO | D656: 46036 | E656: OT | F656: 9135702 | G656: 251.41 | H656: 0 | I656: 251.41 | J656: 0 | K656: 0 | L656: 0
A657: 518 | B657: 1860000210001 | C657: G.A.D. MUNICIPALIDAD DE AMBATO | D657: 46036 | E657: OT | F657: 9135703 | G657: 128.77 | H657: 0 | I657: 128.77 | J657: 0 | K657: 0 | L657: 0
A658: 518 | B658: 1860000210001 | C658: G.A.D. MUNICIPALIDAD DE AMBATO | D658: 46036 | E658: OT | F658: 9135704 | G658: 237.87 | H658: 0 | I658: 237.87 | J658: 0 | K658: 0 | L658: 0
A659: 518 | B659: 1860000210001 | C659: G.A.D. MUNICIPALIDAD DE AMBATO | D659: 46036 | E659: OT | F659: 9135705 | G659: 4.02 | H659: 0 | I659: 4.02 | J659: 0 | K659: 0 | L659: 0
A660: 518 | B660: 1860000210001 | C660: G.A.D. MUNICIPALIDAD DE AMBATO | D660: 46036 | E660: OT | F660: 9135706 | G660: 4.9 | H660: 0 | I660: 4.9 | J660: 0 | K660: 0 | L660: 0
A661: 485 | B661: 1865030070001 | C661: EP-EMAPA-A | D661: 46041 | E661: FE | F661: 4268438 | G661: 76.61 | H661: 0 | I661: 76.61 | J661: 0 | K661: 0 | L661: 0
... A703: 1747 | B703: 1891812015001 | C703: C&A CONSULTING S.C. | D703: 46027 | E703: FE | F703: 47 | G703: 908.89 | H703: 895.45 | I703: 0 | J703: 134.32 | K703: 120.88 | L703: 0

Sheet SRI
A1: RUC_EMISOR | B1: RAZON_SOCIAL_EMISOR | C1: TIPO_COMPROBANTE | D1: SERIE_COMPROBANTE | E1: CLAVE_ACCESO | F1: FECHA_AUTORIZACION | G1: FECHA_EMISION | H1: IDENTIFICACION_RECEPTOR | I1: VALOR_SIN_IMPUESTOS | J1: IVA | K1: IMPORTE_TOTAL | L1: NUMERO_DOCUMENTO_MODIFICADO
A2: 1790283380001 | B2: BANCO DINERS CLUB DEL ECUADOR S.A. | C2: Factura | D2: 001-020-002684239 | E2: 1.012026e+47 | F2: 46023.596 | G2: 46023 | H2: 1891712215001 | I2: 68.57 | J2: 10.28 | K2: 78.85
A3: 1790283380001 | B3: BANCO DINERS CLUB DEL ECUADOR S.A. | C3: Factura | D3: 001-020-002678992 | E3: 1.012026e+47 | F3: 46023.591 | G3: 46023 | H3: 1891712215001 | I3: 47.18 | J3: 7.08 | K3: 54.26
A4: 1865030070001 | B4: EMPRESA PUBLICA - EMPRESA MUNICIPAL DE AGUA POTABLE Y ALCANTARILLADO DE AMBATO | C4: Factura | D4: 001-010-004268390 | E4: 1.012026e+47 | F4: 46030.942 | G4: 46023 | H4: 1891712215001 | I4: 34.6 | J4: 0 | K4: 34.6
A5: 1790283380001 | B5: BANCO DINERS CLUB DEL ECUADOR S.A. | C5: Factura | D5: 001-014-008333084 | E5: 1.012026e+47 | F5: 46024.381 | G5: 46023 | H5: 1891712215001 | I5: 8.3 | J5: 1.24 | K5: 9.54
A6: 1790283380001 | B6: BANCO DINERS CLUB DEL ECUADOR S.A. | C6: Factura | D6: 001-014-008325157 | E6: 1.012026e+47 | F6: 46024.37 | G6: 46023 | H6: 1891712215001 | I6: 50.65 | J6: 7.6 | K6: 58.25
A7: 1790283380001 | B7: BANCO DINERS CLUB DEL ECUADOR S.A. | C7: Factura | D7: 001-020-002685621 | E7: 1.012026e+47 | F7: 46023.597 | G7: 46023 | H7: 1891712215001 | I7: 107.18 | J7: 16.08 | K7: 123.26
A8: 1790283380001 | B8: BANCO DINERS CLUB DEL ECUADOR S.A. | C8: Factura | D8: 001-019-005479265 | E8: 1.012026e+47 | F8: 46023.881 | G8: 46023 | H8: 1891712215001 | I8: 37.2 | J8: 5.58 | K8: 42.78
A9: 1790283380001 | B9: BANCO DINERS CLUB DEL ECUADOR S.A. | C9: Factura | D9: 001-014-008338053 | E9: 1.012026e+47 | F9: 46024.113 | G9: 46023 | H9: 1891712215001 | I9: 30.01 | J9: 4.5 | K9: 34.51
A10: 1790283380001 | B10: BANCO DINERS CLUB DEL ECUADOR S.A. | C10: Factura | D10: 001-014-008249798 | E10: 1.012026e+47 | F10: 46024.271 | G10: 46023 | H10: 1891712215001 | I10: 130.12 | J10: 19.52 | K10: 149.64
A11: 1790283380001 | B11: BANCO DINERS CLUB DEL ECUADOR S.A. | C11: Factura | D11: 001-014-008248148 | E11: 1.012026e+47 | F11: 46024.268 | G11: 46023 | H11: 1891712215001 | I11: 122.72 | J11: 18.41 | K11: 141.13
A12: 1790283380001 | B12: BANCO DINERS CLUB DEL ECUADOR S.A. | C12: Factura | D12: 001-014-008273033 | E12: 1.012026e+47 | F12: 46024.304 | G12: 46023 | H12: 1891712215001 | I12: 171.45 | J12: 25.72 | K12: 197.17
A13: 1790283380001 | B13: BANCO DINERS CLUB DEL ECUADOR S.A. | C13: Factura | D13: 001-014-008268154 | E13: 1.012026e+47 | F13: 46024.298 | G13: 46023 | H13: 1891712215001 | I13: 10.49 | J13: 1.57 | K13: 12.06
... A586: 1802565182001 | B586: ORTIZ LOPEZ EDGAR ENRIQUE | C586: Factura | D586: 001-001-000001532 | E586: 3.1012026e+48 | F586: 46053.419 | G586: 46053 | H586: 1891712215001 | I586: 10 | J586: 1.5 | K586: 11.5

Sheet RESUMEN DE VENTAS
B2: VENTAS BRUTAS | C2: NOTAS DE CREDITO | D2: VENTAS NETAS | E2: IVA | F2: IVA CALCULADO
A3: SERVICIOS TOYOTA CON IVA | B3: 140726.14 | C3: 7132.55 | D3: =+B3-C3 -> 133593.59 | E3: 20039.23 | F3: =+D3*15% -> 20039.038 | G3: =+F3-E3 -> -0.1915
A4: SERVICIOS SUZUKI CON IVA | B4: 58470.99 | C4: 3512.8 | D4: =+B4-C4 -> 54958.19 | E4: 8243.89 | F4: =+D4*15% -> 8243.7285 | G4: =+F4-E4 -> -0.1615
A5: SERVICIOS CHANGAN CON IVA | B5: 15807.37 | C5: 0 | D5: =+B5-C5 -> 15807.37 | E5: 2371.15 | F5: =+D5*15% -> 2371.1055 | G5: =+F5-E5 -> -0.0445
A6: SERVICIOS PEUGEOT CON IVA | B6: 15036.72 | C6: 0 | D6: =+B6-C6 -> 15036.72 | E6: 2255.51 | F6: =+D6*15% -> 2255.508 | G6: =+F6-E6 -> -0.002
A7: SERVICIOS OPEL CON IVA | B7: 0 | C7: 0 | D7: =+B7-C7 -> 0 | E7: 0 | F7: =+D7*15% -> 0 | G7: =+F7-E7 -> 0
A8: SERVICIOS TOYOTA SIN IVA | B8: 2057.85 | C8: 0 | D8: =+B8-C8 -> 2057.85 | E8: 0 | F8: 0 | G8: =+F8-E8 -> 0
A9: SERVICIOS SUZUKI SIN IVA | B9: 0 | C9: 0 | D9: =+B9-C9 -> 0 | E9: 0 | F9: 0 | G9: =+F9-E9 -> 0
A10: SERVICIOS CHANGAN SIN IVA | B10: 0 | C10: 0 | D10: =+B10-C10 -> 0 | E10: 0 | F10: =+D10*15% -> 0 | G10: =+F10-E10 -> 0
A11: SERVICIOS PEUGEOT SIN IVA | B11: 0 | C11: 0 | D11: =+B11-C11 -> 0 | E11: 0 | F11: =+D11*15% -> 0 | G11: =+F11-E11 -> 0
A12: SERVICIOS OPEL SIN IVA | B12: 0 | C12: 0 | D12: =+B12-C12 -> 0 | E12: 0 | F12: =+D12*15% -> 0 | G12: =+F12-E12 -> 0
A13: REPUESTOS TOYOTA CON IVA | B13: 18989.85 | C13: 332.98 | D13: =+B13-C13 -> 18656.87 | E13: 2798.57 | F13: =+D13*15% -> 2798.5305 | G13: =+F13-E13 -> -0.0395
A14: REPUESTOS SUZUKI CON IVA | B14: 9844.37 | C14: 84.55 | D14: =+B14-C14 -> 9759.82 | E14: 1463.98 | F14: =+D14*15% -> 1463.973 | G14: =+F14-E14 -> -0.007
A15: REPUESTOS CHANGAN CON IVA | B15: 2037.53 | C15: 0 | D15: =+B15-C15 -> 2037.53 | E15: 305.64 | F15: =+D15*15% -> 305.6295 | G15: =+F15-E15 -> -0.0105
A16: REPUESTOS PEUGEOT CON IVA | B16: 1788.01 | C16: 0 | D16: =+B16-C16 -> 1788.01 | E16: 268.2 | F16: =+D16*15% -> 268.2015 | G16: =+F16-E16 -> 0.0015
A17: REPUESTOS OPEL CON IVA | B17: 0 | C17: 0 | D17: 0 | E17: 0 | F17: =+D17*15% -> 0 | G17: =+F17-E17 -> 0
A18: REPUESTOS TOYOTA SIN IVA | B18: 0 | C18: 0 | D18: 0 | E18: 0 | F18: =+D18*15% -> 0 | G18: =+F18-E18 -> 0
A19: REPUESTOS SUZUKI SIN IVA | B19: 0 | C19: 0 | D19: 0 | E19: 0 | F19: =+D19*15% -> 0 | G19: =+F19-E19 -> 0
A20: REPUESTOS CHANGAN SIN IVA | B20: 0 | C20: 0 | D20: 0 | E20: 0 | F20: =+D20*15% -> 0 | G20: =+F20-E20 -> 0
A21: REPUESTOS PEUGEOT SIN IVA | B21: 0 | C21: 0 | D21: 0 | E21: 0 | F21: =+D21*15% -> 0 | G21: =+F21-E21 -> 0
A22: REPUESTOS OPEL SIN IVA | B22: 0 | C22: 0 | D22: 0 | E22: 0 | F22: =+D22*15% -> 0 | G22: =+F22-E22 -> 0
A23: OTROS LINEA 7- NO OBJETO IVA | B23: 0 | C23: 0 | D23: 0 | E23: 0 | F23: =+D23*15% -> 0 | G23: =+F23-E23 -> 0
B24: =SUM(B3:B23) -> 264758.83 | C24: =SUM(C3:C23) -> 11062.88 | D24: =SUM(D3:D23) -> 253695.95 | E24: =SUM(E3:E23) -> 37746.17 | F24: =SUM(F3:F23) -> 37745.715 | G24: =+F24-E24 -> -0.455
E26: =+'MAYOR IVA'!K411 -> 37746.16

Sheet LIBRO COMPRAS
A1: CODIGO | B1: CEDULA | C1: NOMBRE | D1: FECHA | E1: TIPO | F1: DOCUMENTO | G1: MONTO | H1: BASE IVA | I1: BASE 0 | J1: IMPUESTOS | K1: RETENCION | L1: SALDO
A2: 432 | B2: 190123626001 | C2: ASEGURADORA DEL SUR C.A. | D2: 46042 | E2: FE | F2: 50638 | G2: 6100.38 | H2: 5304.68 | I2: 0 | J2: 795.7 | K2: 0 | L2: 6100.38
A3: 1416 | B3: 201879962001 | C3: MONTALVO POVEDA IVETTE ANDREA | D3: 46044 | E3: FE | F3: 238 | G3: 98.25 | H3: 0 | I3: 100 | J3: 0 | K3: 1.75 | L3: 98.25
A4: 1416 | B4: 201879962001 | C4: MONTALVO POVEDA IVETTE ANDREA | D4: 46044 | E4: FE | F4: 240 | G4: 98.25 | H4: 0 | I4: 100 | J4: 0 | K4: 1.75 | L4: 98.25
A5: 1310 | B5: 501639371001 | C5: VIZUETE MATA ZOILA TERESA | D5: 46030 | E5: FE | F5: 2 | G5: 180 | H5: 200 | I5: 0 | J5: 30 | K5: 50 | L5: 0
A6: 1610 | B6: 602119992001 | C6: COLCHA LEMA LUIS GONZALO | D6: 46028 | E6: FE | F6: 250 | G6: 263.62 | H6: 0 | I6: 269 | J6: 0 | K6: 5.38 | L6: 263.62
A7: 1610 | B7: 602119992001 | C7: COLCHA LEMA LUIS GONZALO | D7: 46028 | E7: FE | F7: 251 | G7: 187.18 | H7: 0 | I7: 191 | J7: 0 | K7: 3.82 | L7: 187.18
A8: 1610 | B8: 602119992001 | C8: COLCHA LEMA LUIS GONZALO | D8: 46041 | E8: FE | F8: 253 | G8: 49 | H8: 0 | I8: 50 | J8: 0 | K8: 1 | L8: 49
A9: 1610 | B9: 602119992001 | C9: COLCHA LEMA LUIS GONZALO | D9: 46051 | E9: FE | F9: 254 | G9: 441 | H9: 0 | I9: 450 | J9: 0 | K9: 9 | L9: 441
A10: 1844 | B10: 602185464001 | C10: VALVERDE ROBALINO ANGEL BENEDICTO | D10: 46029 | E10: FE | F10: 1841 | G10: 24.58 | H10: 22.61 | I10: 0 | J10: 3.39 | K10: 1.42 | L10: 24.58
A11: 1850 | B11: 604389825001 | C11: CIFUENTES ROSERO ESTHEFANNY MELISSA | D11: 46041 | E11: FE | F11: 2 | G11: 133.3 | H11: 121.74 | I11: 0 | J11: 18.26 | K11: 6.7 | L11: 133.3
A12: 1599 | B12: 604599126001 | C12: AREVALO COLCHA CESAR AUGUSTO | D12: 46027 | E12: FE | F12: 2514 | G12: 18.31 | H12: 17.87 | I12: 0 | J12: 2.68 | K12: 2.24 | L12: 18.31
A13: 1599 | B13: 604599126001 | C13: AREVALO COLCHA CESAR AUGUSTO | D13: 46027 | E13: FE | F13: 2513 | G13: 18.31 | H13: 17.87 | I13: 0 | J13: 2.68 | K13: 2.24 | L13: 18.31
... A501: 518 | B501: 1860000210001 | C501: G.A.D. MUNICIPALIDAD DE AMBATO | D501: 46036 | E501: OT | F501: 9135706 | G501: 4.9 | H501: 0 | I501: 4.9 | J501: 0 | K501: 0 | L501: 0
H502: =SUM(H2:H501) -> 176166.69 | I502: =SUM(I2:I501) -> 7231.33 | J502: =SUM(J2:J501) -> 26425.11
K503: MAYOR IVA
H504: =+H502 -> 176166.69 | I504: =+I502-I508+I693 -> 9174.2 | J504: =+J502-J508 -> 26425.11 | K504: =+'MAYOR IVA'!K306 -> 26425.11 | L504: =+J504-K504 -> 4.3655746e-11
A506: NOTAS DE CRÉDITO
A507: CODIGO | B507: CEDULA | C507: NOMBRE | D507: FECHA | E507: TIPO
A508: 5 | B508: 1790009459001 | C508: CASABACA S.A | D508: 46051 | E508: NE | F508: 2577 | G508: 1543.39 | H508: 0 | I508: 1543.39 | J508: 0 | K508: 0 | L508: 0
A511: RIMPE NEGOCIO POPULAR
A512: CODIGO | B512: CEDULA | C512: NOMBRE | D512: FECHA | E512: TIPO | F512: DOCUMENTO | G512: MONTO | H512: BASE IVA | I512: BASE 0 | J512: IMPUESTOS | K512: RETENCION | L512: SALDO
A513: 1794 | B513: 602001810001 | C513: CHAVEZ ZULA ZOILA | D513: 46028 | E513: BV | F513: 612 | G513: 10 | H513: 0 | I513: 10 | J513: 0 | K513: 0 | L513: 10
A514: 1794 | B514: 602001810001 | C514: CHAVEZ ZULA ZOILA | D514: 46029 | E514: BV | F514: 613 | G514: 10 | H514: 0 | I514: 10 | J514: 0 | K514: 0 | L514: 10
A515: 1794 | B515: 602001810001 | C515: CHAVEZ ZULA ZOILA | D515: 46030 | E515: BV | F515: 614 | G515: 10 | H515: 0 | I515: 10 | J515: 0 | K515: 0 | L515: 10
A516: 1794 | B516: 602001810001 | C516: CHAVEZ ZULA ZOILA | D516: 46030 | E516: BV | F516: 615 | G516: 10 | H516: 0 | I516: 10 | J516: 0 | K516: 0 | L516: 10
A517: 1794 | B517: 602001810001 | C517: CHAVEZ ZULA ZOILA | D517: 46032 | E517: BV | F517: 617 | G517: 10 | H517: 0 | I517: 10 | J517: 0 | K517: 0 | L517: 10
A518: 1794 | B518: 602001810001 | C518: CHAVEZ ZULA ZOILA | D518: 46032 | E518: BV | F518: 618 | G518: 10 | H518: 0 | I518: 10 | J518: 0 | K518: 0 | L518: 10
A519: 1794 | B519: 602001810001 | C519: CHAVEZ ZULA ZOILA | D519: 46037 | E519: BV | F519: 620 | G519: 10 | H519: 0 | I519: 10 | J519: 0 | K519: 0 | L519: 10
A520: 1794 | B520: 602001810001 | C520: CHAVEZ ZULA ZOILA | D520: 46038 | E520: BV | F520: 621 | G520: 10 | H520: 0 | I520: 10 | J520: 0 | K520: 0 | L520: 10
A521: 1794 | B521: 602001810001 | C521: CHAVEZ ZULA ZOILA | D521: 46039 | E521: BV | F521: 622 | G521: 10 | H521: 0 | I521: 10 | J521: 0 | K521: 0 | L521: 10
A522: 1794 | B522: 602001810001 | C522: CHAVEZ ZULA ZOILA | D522: 46041 | E522: BV | F522: 624 | G522: 10 | H522: 0 | I522: 10 | J522: 0 | K522: 0 | L522: 10
A523: 1794 | B523: 602001810001 | C523: CHAVEZ ZULA ZOILA | D523: 46041 | E523: BV | F523: 625 | G523: 10 | H523: 0 | I523: 10 | J523: 0 | K523: 0 | L523: 10
A524: 1794 | B524: 602001810001 | C524: CHAVEZ ZULA ZOILA | D524: 46042 | E524: BV | F524: 626 | G524: 10 | H524: 0 | I524: 10 | J524: 0 | K524: 0 | L524: 10
... A692: 1734 | B692: 1804345385001 | C692: ALLAS BONILLA HECTOR RUBEN | D692: 46036 | E692: BV | F692: 312 | G692: 45 | H692: 0 | I692: 45 | J692: 0 | K692: 0 | L692: 45
H693: =SUM(H513:H692) -> 0 | I693: =SUM(I513:I692) -> 3486.26
A696: ND,OT,TR
A697: CODIGO | B697: CEDULA | C697: NOMBRE | D697: FECHA | E697: TIPO | F697: BASE IVA | G697: BASE 0 | H697: IMPUESTOS | I697: RETENCION | J697: SALDO | K697: DOCUMENTO | L697: MONTO
A698: 355 | B698: 1768152560001 | C698: CORP. NAC.DE TELECOMUNICACIONES CNT E.P. | D698: 46041 | E698: ND | F698: 900293039 | G698: 7.13 | H698: 0 | I698: 7.13 | J698: 0 | K698: 0 | L698: 0
A699: 355 | B699: 1768152560001 | C699: CORP. NAC.DE TELECOMUNICACIONES CNT E.P. | D699: 46041 | E699: ND | F699: 900293033 | G699: 13.8 | H699: 0 | I699: 13.8 | J699: 0 | K699: 0 | L699: 0
A700: 800 | B700: 1791256115001 | C700: OTECEL S.A. | D700: 46041 | E700: ND | F700: 902556998 | G700: 57.5 | H700: 0 | I700: 57.5 | J700: 0 | K700: 0 | L700: 0
A701: 339 | B701: 1791310063001 | C701: DATAFAST S. A. | D701: 46042 | E701: ND | F701: 901453160 | G701: 60.09 | H701: 0 | I701: 60.09 | J701: 0 | K701: 0 | L701: 0
A702: 1522 | B702: 1792967724001 | C702: MEGAWATT-ECUADOR S.A. | D702: 46053 | E702: ND | F702: 1751 | G702: 21.75 | H702: 21.75 | I702: 0 | J702: 0 | K702: 0 | L702: 0
A703: 1410 | B703: 1793107958001 | C703: SZK DEL ECUADOR S.A. | D703: 46034 | E703: ND | F703: 900007724 | G703: 48.3 | H703: 48.3 | I703: 0 | J703: 0 | K703: 0 | L703: 0
A704: 1809 | B704: 1805135306001 | C704: MANTILLA MARIÑO ISAAC GIOVANNI | D704: 46042 | E704: ND | F704: 900000029 | G704: 180 | H704: 0 | I704: 180 | J704: 0 | K704: 0 | L704: 0
A705: 485 | B705: 1865030070001 | C705: EP-EMAPA-A | D705: 46048 | E705: ND | F705: 904268438 | G705: 76.61 | H705: 0 | I705: 76.61 | J705: 0 | K705: 0 | L705: 0
A706: 1351 | B706: 1865033840001 | C706: EMPRESA PUBLICA MUNICIPAL PARA LA GESTION INTEGRAL DE LOS DE | D706: 46048 | E706: ND | F706: 900142458 | G706: 12.85 | H706: 0 | I706: 12.85 | J706: 0 | K706: 0 | L706: 0
A707: 484 | B707: 1890001439001 | C707: EMPRESA ELECTRICA AMBATO S.A. | D707: 46041 | E707: ND | F707: 900246187 | G707: 54.65 | H707: 0 | I707: 54.65 | J707: 0 | K707: 0 | L707: 0
A708: 484 | B708: 1890001439001 | C708: EMPRESA ELECTRICA AMBATO S.A. | D708: 46041 | E708: ND | F708: 900225233 | G708: 892.73 | H708: 0 | I708: 892.73 | J708: 0 | K708: 0 | L708: 0
A709: 1246 | B709: 1891786383001 | C709: CARLARSERVICE CIA. LTDA | D709: 46034 | E709: ND | F709: 800000438 | G709: 6000 | H709: 6000 | I709: 0 | J709: 0 | K709: 0 | L709: 0
... A715: 1497 | B715: 1891804802001 | C715: BACLT INMOBILIARIA S.A.S. | D715: 46045 | E715: TR | F715: 11605402 | G715: 3700 | H715: 0 | I715: 0 | J715: 0 | K715: 0 | L715: 0
A716: 1522 | B716: 1792967724001 | C716: MEGAWATT-ECUADOR S.A. | D716: 46052 | E716: FE | F716: A000001751 | G716: 21.75 | H716: 20 | I716: 0 | J716: 3 | K716: 1.25 | L716: 0
A717: 1410 | B717: 1793107958001 | C717: SZK DEL ECUADOR S.A. | D717: 46032 | E717: FE | F717: A00007724 | G717: 48.3 | H717: 42 | I717: 0 | J717: 6.3 | K717: 0 | L717: 0
A718: 1809 | B718: 1805135306001 | C718: MANTILLA MARIÑO ISAAC GIOVANNI | D718: 46029 | E718: FE | F718: A000000029 | G718: 180 | H718: 0 | I718: 180 | J718: 0 | K718: 0 | L718: 0

Sheet RET PROV
A1: NUM RET | B1: PROVEEDOR | C1: FECHA | D1: FECHA DOC. | E1: TIPO | F1: COD | G1: NUM FACT | H1: % RETEN | I1: BASE | J1: VALOR RETEN | L1: Etiquetas de fila | M1: Suma de BASE | N1: Suma de VALOR RETEN
A2: 32880 | B2: PAEZ ORTIZ CHRISTIAN GONZALO | C2: 46027 | D2: 46027 | E2: IVA | F2: 312 | G2: 3553 | H2: 30 | I2: 0.75 | J2: 0.23 | L2: IVA | M2: 8994.18 | N2: 4700.22
A3: 32880 | B3: PAEZ ORTIZ CHRISTIAN GONZALO | C3: 46027 | D3: 46027 | E3: RENTA | F3: 312 | G3: 3553 | H3: 1.75 | I3: 5 | J3: 0.09 | L3: 30 | M3: 4277.39 | N3: 1283.26 | O3: =+GETPIVOTDATA("Suma de CREDITO",'MAYOR RET'!$M$14,"NOMBRE","10 % RETENCION FUENTE") -> 1616.36
A4: 32881 | B4: BACLT INMOBILIARIA S.A.S. | C4: 46027 | D4: 46027 | E4: IVA | F4: 320 | G4: 192 | H4: 70 | I4: 1251.03 | J4: 875.72 | L4: 70 | M4: 4333.46 | N4: 3033.63 | O4: =+'MAYOR RET'!P21 -> -1283.26
A5: 32881 | B5: BACLT INMOBILIARIA S.A.S. | C5: 46027 | D5: 46027 | E5: RENTA | F5: 320 | G5: 192 | H5: 10 | I5: 8340.2 | J5: 834.02 | L5: 100 | M5: 383.33 | N5: 383.33 | O5: =+GETPIVOTDATA("Suma de CREDITO",'MAYOR RET'!$M$14,"NOMBRE","RETENCION 70% IVA - SERVICIOS") -> 3033.63
A6: 32882 | B6: CARLARSERVICE CIA. LTDA | C6: 46027 | D6: 46027 | E6: RENTA | F6: 303 | G6: 438 | H6: 3 | I6: 10000 | J6: 300 | L6: RENTA | M6: 66506.69 | N6: 2599.79 | O6: =+GETPIVOTDATA("Suma de CREDITO",'MAYOR RET'!$M$14,"NOMBRE","100% RETENCION IVA") -> 383.33
A7: 32882 | B7: CARLARSERVICE CIA. LTDA | C7: 46027 | D7: 46027 | E7: IVA | F7: 303 | G7: 438 | H7: 70 | I7: 1500 | J7: 1050 | L7: 0 | M7: 3486.26 | N7: 0
A8: 32883 | B8: BACLT INMOBILIARIA S.A.S. | C8: 46027 | D8: 46027 | E8: IVA | F8: 320 | G8: 193 | H8: 70 | I8: 790.18 | J8: 553.13 | L8: 1 | M8: 1576.29 | N8: 15.77
A9: 32883 | B9: BACLT INMOBILIARIA S.A.S. | C9: 46027 | D9: 46027 | E9: RENTA | F9: 320 | G9: 193 | H9: 10 | I9: 5267.84 | J9: 526.78 | L9: 1.75 | M9: 28594.14 | N9: 500.42 | O9: =+'MAYOR RET'!P15 -> 15.77
A10: 32884 | B10: PAREDES PADILLA JAZMINA MABEL | C10: 46027 | D10: 46027 | E10: RENTA | F10: 312 | G10: 6232 | H10: 1.75 | I10: 39.13 | J10: 0.68 | L10: 2 | M10: 3342.33 | N10: 66.92 | O10: =+'MAYOR RET'!P16 -> -500.42
A11: 32884 | B11: PAREDES PADILLA JAZMINA MABEL | C11: 46027 | D11: 46027 | E11: IVA | F11: 312 | G11: 6232 | H11: 30 | I11: 5.87 | J11: 1.76 | L11: 3 | M11: 13344.08 | N11: 400.32 | O11: =+GETPIVOTDATA("Suma de CREDITO",'MAYOR RET'!$M$14,"NOMBRE","2 % RETENCION FUENTE") -> 66.92
A12: 32885 | B12: C&A CONSULTING S.C. | C12: 46027 | D12: 46027 | E12: RENTA | F12: 303 | G12: 47 | H12: 3 | I12: 895.45 | J12: 26.86 | L12: 10 | M12: 16163.59 | N12: 1616.36 | O12: =+GETPIVOTDATA("Suma de CREDITO",'MAYOR RET'!$M$14,"NOMBRE","3% RETENCION FUENTE") -> 400.32
A13: 32885 | B13: C&A CONSULTING S.C. | C13: 46027 | D13: 46027 | E13: IVA | F13: 303 | G13: 47 | H13: 70 | I13: 134.32 | J13: 94.02 | L13: Total general | M13: 75500.87 | N13: 7300.01
A14: 32886 | B14: GONZALEZ VEGA EL MOTOR CIA LTDA | C14: 46027 | D14: 46027 | E14: IVA | F14: 312 | G14: 70816 | H14: 30 | I14: 11.92 | J14: 3.58
A15: 32886 | B15: GONZALEZ VEGA EL MOTOR CIA LTDA | C15: 46027 | D15: 46027 | E15: RENTA | F15: 312 | G15: 70816 | H15: 1.75 | I15: 79.45 | J15: 1.39
A16: 32887 | B16: ORTIZ LOPEZ EDGAR ENRIQUE | C16: 46027 | D16: 46027 | E16: IVA | F16: 307 | G16: 1422 | H16: 70 | I16: 1.5 | J16: 1.05
A17: 32887 | B17: ORTIZ LOPEZ EDGAR ENRIQUE | C17: 46027 | D17: 46027 | E17: RENTA | F17: 307 | G17: 1422 | H17: 2 | I17: 10 | J17: 0.2
A18: 32888 | B18: ORTIZ LOPEZ EDGAR ENRIQUE | C18: 46027 | D18: 46027 | E18: RENTA | F18: 307 | G18: 1423 | H18: 2 | I18: 6 | J18: 0.12
A19: 32888 | B19: ORTIZ LOPEZ EDGAR ENRIQUE | C19: 46027 | D19: 46027 | E19: IVA | F19: 307 | G19: 1423 | H19: 70 | I19: 0.9 | J19: 0.63
A20: 32889 | B20: AREVALO COLCHA CESAR AUGUSTO | C20: 46027 | D20: 46027 | E20: RENTA | F20: 307 | G20: 2513 | H20: 2 | I20: 17.87 | J20: 0.36
A21: 32889 | B21: AREVALO COLCHA CESAR AUGUSTO | C21: 46027 | D21: 46027 | E21: IVA | F21: 307 | G21: 2513 | H21: 70 | I21: 2.68 | J21: 1.88
A22: 32890 | B22: ORTIZ LOPEZ EDGAR ENRIQUE | C22: 46027 | D22: 46027 | E22: RENTA | F22: 307 | G22: 1424 | H22: 2 | I22: 8 | J22: 0.16
A23: 32890 | B23: ORTIZ LOPEZ EDGAR ENRIQUE | C23: 46027 | D23: 46027 | E23: IVA | F23: 307 | G23: 1424 | H23: 70 | I23: 1.2 | J23: 0.84
A24: 32891 | B24: ORTIZ LOPEZ EDGAR ENRIQUE | C24: 46027 | D24: 46027 | E24: RENTA | F24: 307 | G24: 1420 | H24: 2 | I24: 10 | J24: 0.2
A25: 32891 | B25: ORTIZ LOPEZ EDGAR ENRIQUE | C25: 46027 | D25: 46027 | E25: IVA | F25: 307 | G25: 1420 | H25: 70 | I25: 1.5 | J25: 1.05
... A788: 33372 | B788: CERON CORDOVA JUAN SEBASTIAN | C788: 46053 | D788: 46053 | E788: RENTA | F788: 332 | G788: 1781 | H788: 0 | I788: 7 | J788: 0
A797: 999999999 | B797: MANTILLA MARIÑO ISAAC GIOVANNI | C797: 46029 | D797: 46029 | F797: 332 | G797: A000000029 | H797: 0 | I797: 180 | J797: 0
A798: 999999999 | B798: MEGAWATT-ECUADOR S.A. | C798: 46052 | D798: 46052 | F798: 312 | G798: A000001751 | H798: 30 | I798: 3 | J798: 0.9
A799: 999999999 | B799: MEGAWATT-ECUADOR S.A. | C799: 46052 | D799: 46052 | F799: 312 | G799: A000001751 | H799: 1.75 | I799: 20 | J799: 0.35

Sheet MAYOR RET
A1: 02.01.06.01.0004 | B1: RETENCION 30% IVA - COMPRAS | C1: N | D1: 21-JAN-26 | E1: BCPI | F1: 247 | G1: 56970273 | H1: ND ND PAGO SRI DECLARACION IVA DI 56970273 | I1: 1119.24 | J1: 0 | K1: 1119.24
A2: 02.01.06.01.0005 | B2: RETENCION 70% IVA - SERVICIOS | C2: N | D2: 21-JAN-26 | E2: BCPI | F2: 247 | G2: 56970273 | H2: ND ND PAGO SRI DECLARACION IVA DI 56970273 | I2: 3421.22 | J2: 0 | K2: 3421.22
A3: 02.01.06.01.0006 | B3: 100% RETENCION IVA | C3: N | D3: 21-JAN-26 | E3: BCPI | F3: 247 | G3: 56970273 | H3: ND ND PAGO SRI DECLARACION IVA DI 56970273 | I3: 383.33 | J3: 0 | K3: 383.33
A4: 02.01.06.02.0002 | B4: 1% RETENCION FUENTE | C4: N | D4: 21-JAN-26 | E4: BCPI | F4: 247 | G4: 56744543 | H4: ND ND PAGO SRI DECLARACION RENTA 56744543 | I4: 9.26 | J4: 0 | K4: 9.26
A5: 02.01.06.02.0003 | B5: 2 % RETENCION FUENTE | C5: N | D5: 21-JAN-26 | E5: BCPI | F5: 247 | G5: 56744543 | H5: ND ND PAGO SRI DECLARACION RENTA 56744543 | I5: 89.38 | J5: 0 | K5: 89.38
A6: 02.01.06.02.0005 | B6: 10 % RETENCION FUENTE | C6: N | D6: 21-JAN-26 | E6: BCPI | F6: 247 | G6: 56744543 | H6: ND ND PAGO SRI DECLARACION RENTA 56744543 | I6: 1616.36 | J6: 0 | K6: 1616.36
A7: 02.01.06.02.0006 | B7: IMPTO. RENTA DE EMPLEADOS | C7: N | D7: 21-JAN-26 | E7: BCPI | F7: 247 | G7: 56744543 | H7: ND ND PAGO SRI DECLARACION RENTA 56744543 | I7: 33.39 | J7: 0 | K7: 33.39
A8: 02.01.06.02.0012 | B8: 1.75% RETENCION FUENTE | C8: N | D8: 21-JAN-26 | E8: BCPI | F8: 247 | G8: 56744543 | H8: ND ND PAGO SRI DECLARACION RENTA 56744543 | I8: 497.9 | J8: 0 | K8: 497.9
A9: 02.01.06.02.0013 | B9: 2.75% RETENCION FUENTE | C9: N | D9: 21-JAN-26 | E9: BCPI | F9: 247 | G9: 56744543 | H9: ND ND PAGO SRI DECLARACION RENTA 56744543 | I9: 3.58 | J9: 0 | K9: 3.58
A10: 02.01.06.02.0021 | B10: 3% RETENCION FUENTE | C10: N | D10: 21-JAN-26 | E10: BCPI | F10: 247 | G10: 56744543 | H10: ND ND PAGO SRI DECLARACION RENTA 56744543 | I10: 469.87 | J10: 0 | K10: 469.87
A14: CUENTA | B14: NOMBRE | C14: N/M | D14: FECHA | E14: TIPO | F14: NO. | G14: EST. | H14: DETALLE | I14: DEBITO | J14: CREDITO | K14: SALDO | M14: Etiquetas de fila | N14: Suma de DEBITO | O14: Suma de CREDITO
A15: 02.01.06.01.0004 | B15: RETENCION 30% IVA - COMPRAS | C15: N | D15: 08-JAN-26 | E15: CP | F15: 113 | G15: 268 | H15: FE NUNEZ NUNEZ OSCAR VINICIO 000000268 | I15: 0 | J15: 24.37 | K15: 1094.87 | M15: 1% RETENCION FUENTE | N15: 0 | O15: 15.77 | P15: =+GETPIVOTDATA("Suma de VALOR RETEN",'RET PROV'!$L$1,"TIPO","RENTA","% RETEN",1) -> 15.77
A16: 02.01.06.01.0004 | B16: RETENCION 30% IVA - COMPRAS | C16: N | D16: 08-JAN-26 | E16: CP | F16: 113 | G16: 269 | H16: FE NUNEZ NUNEZ OSCAR VINICIO 000000269 | I16: 0 | J16: 5.44 | K16: 1089.43 | M16: 1.75% RETENCION FUENTE | N16: 0.35 | O16: 500.77 | P16: =+N16-O16 -> -500.42 | Q16: =+GETPIVOTDATA("Suma de VALOR RETEN",'RET PROV'!$L$1,"TIPO","RENTA","% RETEN",1.75) -> 500.42
A17: 02.01.06.01.0004 | B17: RETENCION 30% IVA - COMPRAS | C17: N | D17: 08-JAN-26 | E17: CP | F17: 113 | G17: 270 | H17: FE NUNEZ NUNEZ OSCAR VINICIO 000000270 | I17: 0 | J17: 3.04 | K17: 1086.39 | M17: 10 % RETENCION FUENTE | N17: 0 | O17: 1616.36 | P17: =+GETPIVOTDATA("Suma de VALOR RETEN",'RET PROV'!$L$1,"TIPO","IVA","% RETEN",10) -> #REF!
A18: 02.01.06.01.0004 | B18: RETENCION 30% IVA - COMPRAS | C18: N | D18: 08-JAN-26 | E18: CP | F18: 113 | G18: 271 | H18: FE NUNEZ NUNEZ OSCAR VINICIO 000000271 | I18: 0 | J18: 13.81 | K18: 1072.58 | M18: 100% RETENCION IVA | N18: 0 | O18: 383.33 | P18: =+GETPIVOTDATA("Suma de VALOR RETEN",'RET PROV'!$L$1,"TIPO","IVA","% RETEN",100) -> 383.33
A19: 02.01.06.01.0004 | B19: RETENCION 30% IVA - COMPRAS | C19: N | D19: 14-JAN-26 | E19: CP | F19: 166 | G19: 1345 | H19: FE CUNALATA VILLACIS HOLGER RA 000001345 | I19: 0 | J19: 8.12 | K19: 1064.46 | M19: 2 % RETENCION FUENTE | N19: 0 | O19: 66.92 | P19: =+GETPIVOTDATA("Suma de VALOR RETEN",'RET PROV'!$L$1,"TIPO","RENTA","% RETEN",2) -> 66.92
A20: 02.01.06.01.0004 | B20: RETENCION 30% IVA - COMPRAS | C20: N | D20: 14-JAN-26 | E20: CP | F20: 166 | G20: 1347 | H20: FE CUNALATA VILLACIS HOLGER RA 000001347 | I20: 0 | J20: 4.28 | K20: 1060.18 | M20: 3% RETENCION FUENTE | N20: 0 | O20: 400.32 | P20: =+GETPIVOTDATA("Suma de VALOR RETEN",'RET PROV'!$L$1,"TIPO","RENTA","% RETEN",3) -> 400.32
A21: 02.01.06.01.0004 | B21: RETENCION 30% IVA - COMPRAS | C21: N | D21: 14-JAN-26 | E21: CP | F21: 166 | G21: 267 | H21: FE NUNEZ NUNEZ OSCAR VINICIO 000000267 | I21: 0 | J21: 84.9 | K21: 975.28 | M21: RETENCION 30% IVA - COMPRAS | N21: 0.9 | O21: 1284.16 | P21: =+N21-O21 -> -1283.26 | Q21: =+GETPIVOTDATA("Suma de VALOR RETEN",'RET PROV'!$L$1,"TIPO","IVA","% RETEN",30) -> 1283.26
A22: 02.01.06.01.0004 | B22: RETENCION 30% IVA - COMPRAS | C22: N | D22: 15-JAN-26 | E22: CP | F22: 186 | G22: 1349 | H22: FE CUNALATA VILLACIS HOLGER RA 000001349 | I22: 0 | J22: 1.92 | K22: 973.36 | M22: RETENCION 70% IVA - SERVICIOS | N22: 0 | O22: 3033.63 | P22: =+GETPIVOTDATA("Suma de VALOR RETEN",'RET PROV'!$L$1,"TIPO","IVA","% RETEN",70) -> 3033.63
A23: 02.01.06.01.0004 | B23: RETENCION 30% IVA - COMPRAS | C23: N | D23: 15-JAN-26 | E23: CP | F23: 186 | G23: 62991 | H23: FE GONZALEZ VEGA EL MOTOR CIA 000062991 | I23: 0 | J23: 3.89 | K23: 969.47 | M23: Total general | N23: 1.25 | O23: 7301.26
A24: 02.01.06.01.0004 | B24: RETENCION 30% IVA - COMPRAS | C24: N | D24: 15-JAN-26 | E24: CP | F24: 186 | G24: 3567 | H24: FE PAEZ ORTIZ CHRISTIAN GONZAL 000003567 | I24: 0 | J24: 4.05 | K24: 965.42
A25: 02.01.06.01.0004 | B25: RETENCION 30% IVA - COMPRAS | C25: N | D25: 19-JAN-26 | E25: CP | F25: 231 | G25: 1429 | H25: FE COMPUMATICA CIA. LTDA. 000001429 | I25: 0 | J25: 1.13 | K25: 964.29
A26: 02.01.06.01.0004 | B26: RETENCION 30% IVA - COMPRAS | C26: N | D26: 19-JAN-26 | E26: CP | F26: 231 | G26: 2987 | H26: FE DISTRIBUIDORA PC-T S.A.S 000002987 | I26: 0 | J26: 1.31 | K26: 962.98
A27: 02.01.06.01.0004 | B27: RETENCION 30% IVA - COMPRAS | C27: N | D27: 23-JAN-26 | E27: CP | F27: 299 | G27: 167 | H27: FE BEDON VACA JOSE LUIS 000000167 | I27: 0 | J27: 7.92 | K27: 955.06
A28: 02.01.06.01.0004 | B28: RETENCION 30% IVA - COMPRAS | C28: N | D28: 23-JAN-26 | E28: CP | F28: 299 | G28: 3579 | H28: FE PAEZ ORTIZ CHRISTIAN GONZAL 000003579 | I28: 0 | J28: 2.7 | K28: 952.36
A29: 02.01.06.01.0004 | B29: RETENCION 30% IVA - COMPRAS | C29: N | D29: 23-JAN-26 | E29: CP | F29: 299 | G29: 3580 | H29: FE PAEZ ORTIZ CHRISTIAN GONZAL 000003580 | I29: 0 | J29: 2.7 | K29: 949.66
A30: 02.01.06.01.0004 | B30: RETENCION 30% IVA - COMPRAS | C30: N | D30: 23-JAN-26 | E30: CP | F30: 299 | G30: 3585 | H30: FE PAEZ ORTIZ CHRISTIAN GONZAL 000003585 | I30: 0 | J30: 0.68 | K30: 948.98
A31: 02.01.06.01.0004 | B31: RETENCION 30% IVA - COMPRAS | C31: N | D31: 31-JAN-26 | E31: CP | F31: 479 | G31: 1751 | H31: ND MEGAWATT-ECUADOR S.A. 000001751 | I31: 0.9 | J31: 0 | K31: 949.88
A32: 02.01.06.01.0004 | B32: RETENCION 30% IVA - COMPRAS | C32: N | D32: 05-JAN-26 | E32: CP | F32: 61 | G32: 3553 | H32: FE PAEZ ORTIZ CHRISTIAN GONZAL 000003553 | I32: 0 | J32: 0.23 | K32: 949.65
A33: 02.01.06.01.0004 | B33: RETENCION 30% IVA - COMPRAS | C33: N | D33: 12-JAN-26 | E33: INVEN | F33: 123 | G33: 521 | H33: IN YANGTSE-AUTO DEL ECUADOR S.A. 000000521 | I33: 0 | J33: 9.32 | K33: 940.33
A34: 02.01.06.01.0004 | B34: RETENCION 30% IVA - COMPRAS | C34: N | D34: 13-JAN-26 | E34: INVEN | F34: 128 | G34: 1049 | H34: IN PULLUQUINGA LASLUISA JORGE LUIS 000001049 | I34: 0 | J34: 1.8 | K34: 938.53
A35: 02.01.06.01.0004 | B35: RETENCION 30% IVA - COMPRAS | C35: N | D35: 13-JAN-26 | E35: INVEN | F35: 128 | G35: 2759 | H35: IN SOLIS SOLIS MARCO VINICIO 000002759 | I35: 0 | J35: 66.98 | K35: 871.55
... A80: 02.01.06.01.0004 | B80: RETENCION 30% IVA - COMPRAS | C80: N | D80: 10-JAN-26 | E80: INVEN | F80: 96 | G80: 519 | H80: IN YANGTSE-AUTO DEL ECUADOR S.A. 000000519 | I80: 0 | J80: 4.94 | K80: 74.13
A81: 02.01.06.01.0004 | B81: RETENCION 30% IVA - COMPRAS | C81: N | D81: 09-JAN-26 | E81: INVSE | F81: 108 | H81: MOV. DE INVENTARIO | I81: 0 | J81: 4.05 | K81: 70.08
A82: 02.01.06.01.0004 | B82: RETENCION 30% IVA - COMPRAS | C82: N | D82: 12-JAN-26 | E82: INVSE | F82: 126 | H82: MOV. DE INVENTARIO | I82: 0 | J82: 15.03 | K82: 55.05
A83: 02.01.06.01.0004 | B83: RETENCION 30% IVA - COMPRAS | C83: N | D83: 14-JAN-26 | E83: INVSE | F83: 153 | H83: MOV. DE INVENTARIO | I83: 0 | J83: 34.73 | K83: 20.32
A84: 02.01.06.01.0004 | B84: RETENCION 30% IVA - COMPRAS | C84: N | D84: 23-JAN-26 | E84: INVSE | F84: 297 | H84: MOV. DE INVENTARIO | I84: 0 | J84: 27.39 | K84: -7.07
A85: 02.01.06.01.0004 | B85: RETENCION 30% IVA - COMPRAS | C85: N | D85: 24-JAN-26 | E85: INVSE | F85: 305 | H85: MOV. DE INVENTARIO | I85: 0 | J85: 10.59 | K85: -17.66
A86: 02.01.06.01.0004 | B86: RETENCION 30% IVA - COMPRAS | C86: N | D86: 28-JAN-26 | E86: INVSE | F86: 350 | H86: MOV. DE INVENTARIO | I86: 0 | J86: 36.65 | K86: -54.31
A87: 02.01.06.01.0004 | B87: RETENCION 30% IVA - COMPRAS | C87: N | D87: 29-JAN-26 | E87: INVSE | F87: 386 | H87: MOV. DE INVENTARIO | I87: 0 | J87: 75.11 | K87: -129.42
A88: 02.01.06.01.0004 | B88: RETENCION 30% IVA - COMPRAS | C88: N | D88: 06-JAN-26 | E88: INVSE | F88: 69 | H88: MOV. DE INVENTARIO | I88: 0 | J88: 34.6 | K88: -164.02
A89: 02.01.06.01.0005 | B89: RETENCION 70% IVA - SERVICIOS | C89: N | D89: 14-JAN-26 | E89: CP | F89: 166 | G89: 1344 | H89: FE CUNALATA VILLACIS HOLGER RA 000001344 | I89: 0 | J89: 12.7 | K89: 3408.52
A90: 02.01.06.01.0005 | B90: RETENCION 70% IVA - SERVICIOS | C90: N | D90: 14-JAN-26 | E90: CP | F90: 166 | G90: 1346 | H90: FE CUNALATA VILLACIS HOLGER RA 000001346 | I90: 0 | J90: 7.21 | K90: 3401.31
A91: 02.01.06.01.0005 | B91: RETENCION 70% IVA - SERVICIOS | C91: N | D91: 15-JAN-26 | E91: CP | F91: 186 | G91: 163 | H91: FE BEDON VACA JOSE LUIS 000000163 | I91: 0 | J91: 6.72 | K91: 3394.59
A92: 02.01.06.01.0005 | B92: RETENCION 70% IVA - SERVICIOS | C92: N | D92: 15-JAN-26 | E92: CP | F92: 186 | G92: 164 | H92: FE BEDON VACA JOSE LUIS 000000164 | I92: 0 | J92: 8.56 | K92: 3386.03
A93: 02.01.06.01.0005 | B93: RETENCION 70% IVA - SERVICIOS | C93: N | D93: 15-JAN-26 | E93: CP | F93: 186 | G93: 165 | H93: FE BEDON VACA JOSE LUIS 000000165 | I93: 0 | J93: 4.38 | K93: 3381.65
A94: 02.01.06.01.0005 | B94: RETENCION 70% IVA - SERVICIOS | C94: N | D94: 15-JAN-26 | E94: CP | F94: 186 | G94: 20594 | H94: FE CAMARA DE COMERCIO DE AMBAT 000020594 | I94: 0 | J94: 17.12 | K94: 3364.53
A95: 02.01.06.01.0005 | B95: RETENCION 70% IVA - SERVICIOS | C95: N | D95: 15-JAN-26 | E95: CP | F95: 186 | G95: 1348 | H95: FE CUNALATA VILLACIS HOLGER RA 000001348 | I95: 0 | J95: 5.73 | K95: 3358.8
A96: 02.01.06.01.0005 | B96: RETENCION 70% IVA - SERVICIOS | C96: N | D96: 17-JAN-26 | E96: CP | F96: 215 | G96: 441 | H96: FE CARLARSERVICE CIA. LTDA 000000441 | I96: 0 | J96: 16.15 | K96: 3342.65
A97: 02.01.06.01.0005 | B97: RETENCION 70% IVA - SERVICIOS | C97: N | D97: 17-JAN-26 | E97: CP | F97: 215 | G97: 443 | H97: FE CARLARSERVICE CIA. LTDA 000000443 | I97: 0 | J97: 47.64 | K97: 3295.01
A98: 02.01.06.01.0005 | B98: RETENCION 70% IVA - SERVICIOS | C98: N | D98: 17-JAN-26 | E98: CP | F98: 215 | G98: 445 | H98: FE CARLARSERVICE CIA. LTDA 000000445 | I98: 0 | J98: 24.87 | K98: 3270.14
A99: 02.01.06.01.0005 | B99: RETENCION 70% IVA - SERVICIOS | C99: N | D99: 05-JAN-26 | E99: CP | F99: 61 | G99: 192 | H99: FE BACLT INMOBILIARIA S.A.S. 000000192 | I99: 0 | J99: 875.72 | K99: 2394.42
A100: 02.01.06.01.0005 | B100: RETENCION 70% IVA - SERVICIOS | C100: N | D100: 05-JAN-26 | E100: CP | F100: 61 | G100: 193 | H100: FE BACLT INMOBILIARIA S.A.S. 000000193 | I100: 0 | J100: 553.13 | K100: 1841.29
... A103: 02.01.06.01.0005 | B103: RETENCION 70% IVA - SERVICIOS | C103: N | D103: 06-JAN-26 | E103: CP | F103: 71 | G103: 161 | H103: FE BEDON VACA JOSE LUIS 000000161 | I103: 0 | J103: 3.4 | K103: 693.87
A104: 02.01.06.01.0005 | B104: RETENCION 70% IVA - SERVICIOS | C104: N | D104: 08-JAN-26 | E104: SUBCO | F104: 102 | H104: SUBCONTRATOS | I104: 0 | J104: 16.8 | K104: 677.07
A105: 02.01.06.01.0005 | B105: RETENCION 70% IVA - SERVICIOS | C105: N | D105: 08-JAN-26 | E105: SUBCO | F105: 103 | H105: SUBCONTRATOS | I105: 0 | J105: 5.64 | K105: 671.43
A106: 02.01.06.01.0005 | B106: RETENCION 70% IVA - SERVICIOS | C106: N | D106: 09-JAN-26 | E106: SUBCO | F106: 107 | H106: SUBCONTRATOS | I106: 0 | J106: 9.98 | K106: 661.45
A107: 02.01.06.01.0005 | B107: RETENCION 70% IVA - SERVICIOS | C107: N | D107: 09-JAN-26 | E107: SUBCO | F107: 109 | H107: SUBCONTRATOS | I107: 0 | J107: 3.76 | K107: 657.69
A108: 02.01.06.01.0005 | B108: RETENCION 70% IVA - SERVICIOS | C108: N | D108: 10-JAN-26 | E108: SUBCO | F108: 111 | H108: SUBCONTRATOS | I108: 0 | J108: 5.88 | K108: 651.81
A109: 02.01.06.01.0005 | B109: RETENCION 70% IVA - SERVICIOS | C109: N | D109: 12-JAN-26 | E109: SUBCO | F109: 125 | H109: SUBCONTRATOS | I109: 0 | J109: 18.8 | K109: 633.01
A110: 02.01.06.01.0005 | B110: RETENCION 70% IVA - SERVICIOS | C110: N | D110: 13-JAN-26 | E110: SUBCO | F110: 134 | H110: SUBCONTRATOS | I110: 0 | J110: 5.36 | K110: 627.65
A111: 02.01.06.01.0005 | B111: RETENCION 70% IVA - SERVICIOS | C111: N | D111: 14-JAN-26 | E111: SUBCO | F111: 150 | H111: SUBCONTRATOS | I111: 0 | J111: 7.35 | K111: 620.3
A112: 02.01.06.01.0005 | B112: RETENCION 70% IVA - SERVICIOS | C112: N | D112: 14-JAN-26 | E112: SUBCO | F112: 152 | H112: SUBCONTRATOS | I112: 0 | J112: 5.46 | K112: 614.84
A113: 02.01.06.01.0005 | B113: RETENCION 70% IVA - SERVICIOS | C113: N | D113: 15-JAN-26 | E113: SUBCO | F113: 183 | H113: SUBCONTRATOS | I113: 0 | J113: 2.73 | K113: 612.11
A114: 02.01.06.01.0005 | B114: RETENCION 70% IVA - SERVICIOS | C114: N | D114: 15-JAN-26 | E114: SUBCO | F114: 185 | H114: SUBCONTRATOS | I114: 0 | J114: 2.14 | K114: 609.97
A115: 02.01.06.01.0005 | B115: RETENCION 70% IVA - SERVICIOS | C115: N | D115: 16-JAN-26 | E115: SUBCO | F115: 191 | H115: SUBCONTRATOS | I115: 0 | J115: 13.86 | K115: 596.11
... A146: 02.01.06.01.0005 | B146: RETENCION 70% IVA - SERVICIOS | C146: N | D146: 07-JAN-26 | E146: SUBCO | F146: 79 | H146: SUBCONTRATOS | I146: 0 | J146: 7.84 | K146: 387.59
A147: 02.01.06.01.0006 | B147: 100% RETENCION IVA | C147: N | D147: 08-JAN-26 | E147: CP | F147: 113 | G147: 77 | H147: FE MERA VASQUEZ NELLY MAGDALEN 000000077 | I147: 0 | J147: 270 | K147: 113.33
A148: 02.01.06.01.0006 | B148: 100% RETENCION IVA | C148: N | D148: 08-JAN-26 | E148: CP | F148: 113 | G148: 2 | H148: FE VIZUETE MATA ZOILA TERESA 000000002 | I148: 0 | J148: 30 | K148: 83.33
A149: 02.01.06.01.0006 | B149: 100% RETENCION IVA | C149: N | D149: 06-JAN-26 | E149: CP | F149: 71 | G149: 1555 | H149: FE ARIAS MANTILLA JUAN FERNAND 000001555 | I149: 0 | J149: 83.33 | K149: 0
A150: 02.01.06.02.0002 | B150: 1% RETENCION FUENTE | C150: N | D150: 22-JAN-26 | E150: CP | F150: 286 | G150: 627 | H150: FE GOMEZ CORDOVA EDWIN ROLANDO 000000627 | I150: 0 | J150: 2.01 | K150: 7.25
A151: 02.01.06.02.0002 | B151: 1% RETENCION FUENTE | C151: N | D151: 19-JAN-26 | E151: INVEN | F151: 222 | G151: 2 | H151: IN CIFUENTES ROSERO ESTHEFANNY MELISSA 000000002 | I151: 0 | J151: 1.22 | K151: 6.03
A152: 02.01.06.02.0002 | B152: 1% RETENCION FUENTE | C152: N | D152: 08-JAN-26 | E152: SUBCO | F152: 102 | H152: SUBCONTRATOS | I152: 0 | J152: 1 | K152: 5.03
A153: 02.01.06.02.0002 | B153: 1% RETENCION FUENTE | C153: N | D153: 09-JAN-26 | E153: SUBCO | F153: 107 | H153: SUBCONTRATOS | I153: 0 | J153: 0.59 | K153: 4.44
A154: 02.01.06.02.0002 | B154: 1% RETENCION FUENTE | C154: N | D154: 10-JAN-26 | E154: SUBCO | F154: 111 | H154: SUBCONTRATOS | I154: 0 | J154: 0.4 | K154: 4.04
A155: 02.01.06.02.0002 | B155: 1% RETENCION FUENTE | C155: N | D155: 12-JAN-26 | E155: SUBCO | F155: 125 | H155: SUBCONTRATOS | I155: 0 | J155: 1.25 | K155: 2.79
A156: 02.01.06.02.0002 | B156: 1% RETENCION FUENTE | C156: N | D156: 13-JAN-26 | E156: SUBCO | F156: 134 | H156: SUBCONTRATOS | I156: 0 | J156: 0.35 | K156: 2.44
A157: 02.01.06.02.0002 | B157: 1% RETENCION FUENTE | C157: N | D157: 14-JAN-26 | E157: SUBCO | F157: 152 | H157: SUBCONTRATOS | I157: 0 | J157: 0.3 | K157: 2.14
A158: 02.01.06.02.0002 | B158: 1% RETENCION FUENTE | C158: N | D158: 16-JAN-26 | E158: SUBCO | F158: 191 | H158: SUBCONTRATOS | I158: 0 | J158: 0.9 | K158: 1.24
A159: 02.01.06.02.0002 | B159: 1% RETENCION FUENTE | C159: N | D159: 20-JAN-26 | E159: SUBCO | F159: 236 | H159: SUBCONTRATOS | I159: 0 | J159: 0.8 | K159: 0.44
A160: 02.01.06.02.0002 | B160: 1% RETENCION FUENTE | C160: N | D160: 21-JAN-26 | E160: SUBCO | F160: 266 | H160: SUBCONTRATOS | I160: 0 | J160: 1.24 | K160: -0.8
A161: 02.01.06.02.0002 | B161: 1% RETENCION FUENTE | C161: N | D161: 22-JAN-26 | E161: SUBCO | F161: 283 | H161: SUBCONTRATOS | I161: 0 | J161: 0.88 | K161: -1.68
A162: 02.01.06.02.0002 | B162: 1% RETENCION FUENTE | C162: N | D162: 23-JAN-26 | E162: SUBCO | F162: 298 | H162: SUBCONTRATOS | I162: 0 | J162: 0.6 | K162: -2.28
A163: 02.01.06.02.0002 | B163: 1% RETENCION FUENTE | C163: N | D163: 26-JAN-26 | E163: SUBCO | F163: 336 | H163: SUBCONTRATOS | I163: 0 | J163: 0.22 | K163: -2.5
... A169: 02.01.06.02.0002 | B169: 1% RETENCION FUENTE | C169: N | D169: 07-JAN-26 | E169: SUBCO | F169: 77 | H169: SUBCONTRATOS | I169: 0 | J169: 0.54 | K169: -6.51
A170: 02.01.06.02.0003 | B170: 2 % RETENCION FUENTE | C170: N | D170: 14-JAN-26 | E170: CP | F170: 166 | G170: 1344 | H170: FE CUNALATA VILLACIS HOLGER RA 000001344 | I170: 0 | J170: 2.42 | K170: 86.96
A171: 02.01.06.02.0003 | B171: 2 % RETENCION FUENTE | C171: N | D171: 14-JAN-26 | E171: CP | F171: 166 | G171: 1346 | H171: FE CUNALATA VILLACIS HOLGER RA 000001346 | I171: 0 | J171: 1.37 | K171: 85.59
A172: 02.01.06.02.0003 | B172: 2 % RETENCION FUENTE | C172: N | D172: 15-JAN-26 | E172: CP | F172: 186 | G172: 163 | H172: FE BEDON VACA JOSE LUIS 000000163 | I172: 0 | J172: 1.28 | K172: 84.31
A173: 02.01.06.02.0003 | B173: 2 % RETENCION FUENTE | C173: N | D173: 15-JAN-26 | E173: CP | F173: 186 | G173: 164 | H173: FE BEDON VACA JOSE LUIS 000000164 | I173: 0 | J173: 1.63 | K173: 82.68
A174: 02.01.06.02.0003 | B174: 2 % RETENCION FUENTE | C174: N | D174: 15-JAN-26 | E174: CP | F174: 186 | G174: 165 | H174: FE BEDON VACA JOSE LUIS 000000165 | I174: 0 | J174: 0.83 | K174: 81.85
A175: 02.01.06.02.0003 | B175: 2 % RETENCION FUENTE | C175: N | D175: 15-JAN-26 | E175: CP | F175: 186 | G175: 1348 | H175: FE CUNALATA VILLACIS HOLGER RA 000001348 | I175: 0 | J175: 1.09 | K175: 80.76
A176: 02.01.06.02.0003 | B176: 2 % RETENCION FUENTE | C176: N | D176: 06-JAN-26 | E176: CP | F176: 71 | G176: 161 | H176: FE BEDON VACA JOSE LUIS 000000161 | I176: 0 | J176: 0.65 | K176: 80.11
A177: 02.01.06.02.0003 | B177: 2 % RETENCION FUENTE | C177: N | D177: 08-JAN-26 | E177: SUBCO | F177: 102 | H177: SUBCONTRATOS | I177: 0 | J177: 1.2 | K177: 78.91
A178: 02.01.06.02.0003 | B178: 2 % RETENCION FUENTE | C178: N | D178: 08-JAN-26 | E178: SUBCO | F178: 103 | H178: SUBCONTRATOS | I178: 0 | J178: 1.08 | K178: 77.83
A179: 02.01.06.02.0003 | B179: 2 % RETENCION FUENTE | C179: N | D179: 09-JAN-26 | E179: SUBCO | F179: 107 | H179: SUBCONTRATOS | I179: 0 | J179: 1.92 | K179: 75.91
A180: 02.01.06.02.0003 | B180: 2 % RETENCION FUENTE | C180: N | D180: 09-JAN-26 | E180: SUBCO | F180: 109 | H180: SUBCONTRATOS | I180: 0 | J180: 0.72 | K180: 75.19
A181: 02.01.06.02.0003 | B181: 2 % RETENCION FUENTE | C181: N | D181: 10-JAN-26 | E181: SUBCO | F181: 111 | H181: SUBCONTRATOS | I181: 0 | J181: 0.32 | K181: 74.87
A182: 02.01.06.02.0003 | B182: 2 % RETENCION FUENTE | C182: N | D182: 12-JAN-26 | E182: SUBCO | F182: 125 | H182: SUBCONTRATOS | I182: 0 | J182: 1.08 | K182: 73.79
A183: 02.01.06.02.0003 | B183: 2 % RETENCION FUENTE | C183: N | D183: 13-JAN-26 | E183: SUBCO | F183: 134 | H183: SUBCONTRATOS | I183: 0 | J183: 0.32 | K183: 73.47
A184: 02.01.06.02.0003 | B184: 2 % RETENCION FUENTE | C184: N | D184: 14-JAN-26 | E184: SUBCO | F184: 150 | H184: SUBCONTRATOS | I184: 0 | J184: 1.4 | K184: 72.07
...

Sheet MAYOR IVA
A1: CUENTA | B1: NOMBRE | C1: N/M | D1: FECHA | E1: TIPO | F1: NO. | G1: EST. | H1: DETALLE | I1: DEBITO | J1: CREDITO | K1: SALDO
A2: 02.01.06.01.0018 | B2: 15% IVA | C2: N | D2: 08-JAN-26 | E2: CP | F2: 113 | G2: 77 | H2: FE MERA VASQUEZ NELLY MAGDALEN 000000077 | I2: 270 | J2: 0 | K2: 270
A3: 02.01.06.01.0018 | B3: 15% IVA | C3: N | D3: 08-JAN-26 | E3: CP | F3: 113 | G3: 268 | H3: FE NUNEZ NUNEZ OSCAR VINICIO 000000268 | I3: 81.23 | J3: 0 | K3: 351.23
A4: 02.01.06.01.0018 | B4: 15% IVA | C4: N | D4: 08-JAN-26 | E4: CP | F4: 113 | G4: 269 | H4: FE NUNEZ NUNEZ OSCAR VINICIO 000000269 | I4: 18.13 | J4: 0 | K4: 369.36
A5: 02.01.06.01.0018 | B5: 15% IVA | C5: N | D5: 08-JAN-26 | E5: CP | F5: 113 | G5: 270 | H5: FE NUNEZ NUNEZ OSCAR VINICIO 000000270 | I5: 10.12 | J5: 0 | K5: 379.48
A6: 02.01.06.01.0018 | B6: 15% IVA | C6: N | D6: 08-JAN-26 | E6: CP | F6: 113 | G6: 271 | H6: FE NUNEZ NUNEZ OSCAR VINICIO 000000271 | I6: 46.03 | J6: 0 | K6: 425.51
A7: 02.01.06.01.0018 | B7: 15% IVA | C7: N | D7: 08-JAN-26 | E7: CP | F7: 113 | G7: 2 | H7: FE VIZUETE MATA ZOILA TERESA 000000002 | I7: 30 | J7: 0 | K7: 455.51
A8: 02.01.06.01.0018 | B8: 15% IVA | C8: N | D8: 09-JAN-26 | E8: CP | F8: 114 | G8: 919 | H8: FE CENTRO DE SERVICIOS COMPART 000000919 | I8: 240.64 | J8: 0 | K8: 696.15
A9: 02.01.06.01.0018 | B9: 15% IVA | C9: N | D9: 12-JAN-26 | E9: CP | F9: 127 | G9: 245293033 | H9: FE CORP. NAC.DE TELECOMUNICACI 245293033 | I9: 1.8 | J9: 0 | K9: 697.95
A10: 02.01.06.01.0018 | B10: 15% IVA | C10: N | D10: 12-JAN-26 | E10: CP | F10: 127 | G10: 245293038 | H10: FE CORP. NAC.DE TELECOMUNICACI 245293038 | I10: 0.93 | J10: 0 | K10: 698.88
A11: 02.01.06.01.0018 | B11: 15% IVA | C11: N | D11: 12-JAN-26 | E11: CP | F11: 127 | G11: 122556998 | H11: FE OTECEL S.A. 122556998 | I11: 7.5 | J11: 0 | K11: 706.38
A12: 02.01.06.01.0018 | B12: 15% IVA | C12: N | D12: 12-JAN-26 | E12: CP | F12: 127 | G12: 7724 | H12: FE SZK DEL ECUADOR S.A. 000007724 | I12: 5.67 | J12: 0 | K12: 712.05
A13: 02.01.06.01.0018 | B13: 15% IVA | C13: N | D13: 12-JAN-26 | E13: CP | F13: 127 | G13: 900007724 | H13: ND SZK DEL ECUADOR S.A. 900007724 | I13: 0 | J13: 6.3 | K13: 705.75
... A244: 02.01.06.01.0018 | B244: 15% IVA | C244: N | D244: 10-JAN-26 | E244: INVEN | F244: 99 | G244: 5368 | H244: IN SZK DEL ECUADOR S.A. 000005368 | I244: 25.68 | J244: 0 | K244: 23321.57
A245: 02.01.06.01.0018 | B245: 15% IVA | C245: N | D245: 09-JAN-26 | E245: INVSE | F245: 105 | H245: MOV. DE INVENTARIO | I245: 457.24 | J245: 0 | K245: 23778.81
A246: 02.01.06.01.0018 | B246: 15% IVA | C246: N | D246: 09-JAN-26 | E246: INVSE | F246: 108 | H246: MOV. DE INVENTARIO | I246: 35.59 | J246: 0 | K246: 23814.4
A247: 02.01.06.01.0018 | B247: 15% IVA | C247: N | D247: 12-JAN-26 | E247: INVSE | F247: 126 | H247: MOV. DE INVENTARIO | I247: 50.09 | J247: 0 | K247: 23864.49
A248: 02.01.06.01.0018 | B248: 15% IVA | C248: N | D248: 13-JAN-26 | E248: INVSE | F248: 132 | H248: MOV. DE INVENTARIO | I248: 103.08 | J248: 0 | K248: 23967.57
A249: 02.01.06.01.0018 | B249: 15% IVA | C249: N | D249: 13-JAN-26 | E249: INVSE | F249: 135 | H249: MOV. DE INVENTARIO | I249: 144.14 | J249: 0 | K249: 24111.71
A250: 02.01.06.01.0018 | B250: 15% IVA | C250: N | D250: 14-JAN-26 | E250: INVSE | F250: 153 | H250: MOV. DE INVENTARIO | I250: 115.75 | J250: 0 | K250: 24227.46
A251: 02.01.06.01.0018 | B251: 15% IVA | C251: N | D251: 15-JAN-26 | E251: INVSE | F251: 182 | H251: MOV. DE INVENTARIO | I251: 88.03 | J251: 0 | K251: 24315.49
A252: 02.01.06.01.0018 | B252: 15% IVA | C252: N | D252: 15-JAN-26 | E252: INVSE | F252: 184 | H252: MOV. DE INVENTARIO | I252: 39.62 | J252: 0 | K252: 24355.11
A253: 02.01.06.01.0018 | B253: 15% IVA | C253: N | D253: 22-JAN-26 | E253: INVSE | F253: 284 | H253: MOV. DE INVENTARIO | I253: 144.14 | J253: 0 | K253: 24499.25
A254: 02.01.06.01.0018 | B254: 15% IVA | C254: N | D254: 23-JAN-26 | E254: INVSE | F254: 297 | H254: MOV. DE INVENTARIO | I254: 91.31 | J254: 0 | K254: 24590.56
A255: 02.01.06.01.0018 | B255: 15% IVA | C255: N | D255: 24-JAN-26 | E255: INVSE | F255: 305 | H255: MOV. DE INVENTARIO | I255: 79.46 | J255: 0 | K255: 24670.02
A256: 02.01.06.01.0018 | B256: 15% IVA | C256: N | D256: 26-JAN-26 | E256: INVSE | F256: 334 | H256: MOV. DE INVENTARIO | I256: 457.24 | J256: 0 | K256: 25127.26
... A304: 02.01.06.01.0018 | B304: 15% IVA | C304: N | D304: 07-JAN-26 | E304: SUBCO | F304: 79 | H304: SUBCONTRATOS | I304: 11.17 | J304: 0 | K304: 21588.72
I305: =SUM(I2:I304) -> 26434.41 | J305: =SUM(J2:J304) -> 9.3
K306: =+I305-J305 -> 26425.11
A316: 02.01.06.01.0018 | B316: 15% IVA | C316: N | D316: 05-JAN-26 | E316: REPTO | F316: 414 | H316: MOD. REPUESTOS REP01 | I316: 0 | J316: 35.25 | K316: 25952.61
A317: 02.01.06.01.0018 | B317: 15% IVA | C317: N | D317: 06-JAN-26 | E317: REPTO | F317: 415 | H317: MOD. REPUESTOS REP01 | I317: 0 | J317: 714.03 | K317: 25238.58
A318: 02.01.06.01.0018 | B318: 15% IVA | C318: N | D318: 07-JAN-26 | E318: REPTO | F318: 416 | H318: MOD. REPUESTOS REP01 | I318: 0 | J318: 110.79 | K318: 25127.79
A319: 02.01.06.01.0018 | B319: 15% IVA | C319: N | D319: 09-JAN-26 | E319: REPTO | F319: 417 | H319: MOD. REPUESTOS REP01 | I319: 0 | J319: 38.26 | K319: 25089.53
A320: 02.01.06.01.0018 | B320: 15% IVA | C320: N | D320: 10-JAN-26 | E320: REPTO | F320: 418 | H320: MOD. REPUESTOS REP01 | I320: 0 | J320: 23.24 | K320: 25066.29
A321: 02.01.06.01.0018 | B321: 15% IVA | C321: N | D321: 12-JAN-26 | E321: REPTO | F321: 419 | H321: MOD. REPUESTOS REP01 | I321: 0 | J321: 29.12 | K321: 25037.17
A322: 02.01.06.01.0018 | B322: 15% IVA | C322: N | D322: 13-JAN-26 | E322: REPTO | F322: 420 | H322: MOD. REPUESTOS REP01 | I322: 0 | J322: 6.16 | K322: 25031.01
A323: 02.01.06.01.0018 | B323: 15% IVA | C323: N | D323: 14-JAN-26 | E323: REPTO | F323: 421 | H323: MOD. REPUESTOS REP01 | I323: 0 | J323: 14.98 | K323: 25016.03
A324: 02.01.06.01.0018 | B324: 15% IVA | C324: N | D324: 15-JAN-26 | E324: REPTO | F324: 422 | H324: MOD. REPUESTOS REP01 | I324: 49.95 | J324: 0 | K324: 25065.98
A325: 02.01.06.01.0018 | B325: 15% IVA | C325: N | D325: 16-JAN-26 | E325: REPTO | F325: 423 | H325: MOD. REPUESTOS REP01 | I325: 0 | J325: 72.4 | K325: 24993.58
A326: 02.01.06.01.0018 | B326: 15% IVA | C326: N | D326: 17-JAN-26 | E326: REPTO | F326: 424 | H326: MOD. REPUESTOS REP01 | I326: 0 | J326: 117.89 | K326: 24875.69
A327: 02.01.06.01.0018 | B327: 15% IVA | C327: N | D327: 19-JAN-26 | E327: REPTO | F327: 425 | H327: MOD. REPUESTOS REP01 | I327: 0 | J327: 120.96 | K327: 24754.73
... A390: 02.01.06.01.0018 | B390: 15% IVA | C390: N | D390: 31-JAN-26 | E390: REPTO | F390: 480 | H390: MOD. REPUESTOS REP08 | I390: 0 | J390: 38.76 | K390: 21151.47
I391: =SUM(I316:I390) -> 62.63 | J391: =SUM(J316:J390) -> 4899.02
K392: =+J391-I391 -> 4836.39
A394: 02.01.06.01.0018 | B394: 15% IVA | C394: N | D394: 31-JAN-26 | E394: VENSE | F394: 400 | H394: CONTA VENTAS - CENTRO01 PERIODO 2026 - 01 | I394: 0 | J394: 11917.3 | K394: 9671.42
A395: 02.01.06.01.0018 | B395: 15% IVA | C395: N | D395: 31-JAN-26 | E395: VENSE | F395: 400 | H395: CONTA VENTAS - CENTRO01 PERIODO 2026 - 01 | I395: 0 | J395: 9191.81 | K395: 479.61
A396: 02.01.06.01.0018 | B396: 15% IVA | C396: N | D396: 31-JAN-26 | E396: VENSE | F396: 401 | H396: CONTABILIZACION VENTAS - CENTRO01 PERIODO 2026 - 01 | I396: 1069.88 | J396: 0 | K396: 1549.49
A397: 02.01.06.01.0018 | B397: 15% IVA | C397: N | D397: 31-JAN-26 | E397: VENSE | F397: 407 | H397: CONTA VENTAS - CENTRO07 PERIODO 2026 - 01 | I397: 0 | J397: 3479.77 | K397: -1930.28
A398: 02.01.06.01.0018 | B398: 15% IVA | C398: N | D398: 31-JAN-26 | E398: VENSE | F398: 407 | H398: CONTA VENTAS - CENTRO07 PERIODO 2026 - 01 | I398: 0 | J398: 3127.52 | K398: -5057.8
A399: 02.01.06.01.0018 | B399: 15% IVA | C399: N | D399: 31-JAN-26 | E399: VENSE | F399: 408 | H399: CONTABILIZACION VENTAS - CENTRO07 PERIODO 2026 - 01 | I399: 86.18 | J399: 0 | K399: -4971.62
A400: 02.01.06.01.0018 | B400: 15% IVA | C400: N | D400: 31-JAN-26 | E400: VENSE | F400: 409 | H400: CONTA VENTAS - CENTRO08 PERIODO 2026 - 01 | I400: 0 | J400: 1047.94 | K400: -6019.56
A401: 02.01.06.01.0018 | B401: 15% IVA | C401: N | D401: 31-JAN-26 | E401: VENSE | F401: 409 | H401: CONTA VENTAS - CENTRO08 PERIODO 2026 - 01 | I401: 0 | J401: 1115.57 | K401: -7135.13
A402: 02.01.06.01.0018 | B402: 15% IVA | C402: N | D402: 31-JAN-26 | E402: VENSE | F402: 410 | H402: CONTABILIZACION VENTAS - CENTRO08 PERIODO 2026 - 01 | I402: 440.74 | J402: 0 | K402: -6694.39
A403: 02.01.06.01.0018 | B403: 15% IVA | C403: N | D403: 31-JAN-26 | E403: VENSE | F403: 411 | H403: CONTA VENTAS - CENTRO05 PERIODO 2026 - 01 | I403: 0 | J403: 1516.93 | K403: -8211.32
A404: 02.01.06.01.0018 | B404: 15% IVA | C404: N | D404: 31-JAN-26 | E404: VENSE | F404: 411 | H404: CONTA VENTAS - CENTRO05 PERIODO 2026 - 01 | I404: 0 | J404: 644.58 | K404: -8855.9
A405: 02.01.06.01.0018 | B405: 15% IVA | C405: N | D405: 31-JAN-26 | E405: VENSE | F405: 412 | H405: CONTA VENTAS - CENTRO08 PERIODO 2026 - 01 | I405: 0 | J405: 209.64 | K405: -9065.54
... A407: 02.01.06.01.0018 | B407: 15% IVA | C407: N | D407: 31-JAN-26 | E407: VENSE | F407: 413 | H407: CONTA VENTAS - CENTRO06 PERIODO 2026 - 01 | I407: 0 | J407: 1319.47 | K407: -11321.05
I408: =SUM(I394:I407) -> 1596.8 | J408: =SUM(J394:J407) -> 34506.57
J409: =+J408-I408 -> 32909.77
K411: =+J409+K392 -> 37746.16
